helpnow/__init__.py
helpnow/app.py
helpnow/configuracao_sistema.py
helpnow/daos.py
helpnow/firebase_config.py
helpnow/gerenciador_sistema.py
helpnow/modelos_helpdesk.py
helpnow/seguranca.py
helpnow/template_methods.py
helpnow/static/style.css
helpnow/templates/adicionar_mensagem.html
helpnow/templates/atribuir_ticket.html
helpnow/templates/avaliar_ticket.html
helpnow/templates/base.html
helpnow/templates/cadastrar_agente.html
helpnow/templates/cadastrar_usuario.html
helpnow/templates/criar_ticket.html
helpnow/templates/gerenciar_ativos.html
helpnow/templates/gerenciar_categorias.html
helpnow/templates/gerenciar_especialidades.html
helpnow/templates/gerenciar_slas.html
helpnow/templates/gerenciar_usuarios.html
helpnow/templates/index.html
helpnow/templates/listar_feedbacks.html
helpnow/templates/login.html
helpnow/templates/painel_agente.html
helpnow/templates/relatorio.html
helpnow/templates/ver_meus_tickets.html
helpnow-0.1.0.dist-info/licenses/LICENSE
helpnow-0.1.0.dist-info/METADATA
helpnow-0.1.0.dist-info/WHEEL
helpnow-0.1.0.dist-info/top_level.txt
helpnow-0.1.0.dist-info/RECORD
