Metadata-Version: 2.4
Name: helpnow
Version: 0.1.0
Summary: Plataforma de helpdesk Flask integrada ao Firebase.
Author: HelpNow Contributors
License: MIT License
Project-URL: Homepage, https://github.com/your-org/helpnow
Project-URL: Documentation, https://github.com/your-org/helpnow#readme
Requires-Python: >=3.9
License-File: LICENSE
Requires-Dist: Flask>=2.2
Requires-Dist: firebase-admin>=6.0
Requires-Dist: dacite>=1.8
Requires-Dist: passlib[bcrypt]>=1.7
Provides-Extra: dev
Requires-Dist: pytest>=7.0; extra == "dev"
Requires-Dist: build>=1.0; extra == "dev"
Requires-Dist: twine>=4.0; extra == "dev"
Dynamic: license-file
